seqconverter.py
seqconverter-3.4.1.dist-info/LICENSE
seqconverter-3.4.1.dist-info/METADATA
seqconverter-3.4.1.dist-info/WHEEL
seqconverter-3.4.1.dist-info/entry_points.txt
seqconverter-3.4.1.dist-info/top_level.txt
seqconverter-3.4.1.dist-info/RECORD
