Metadata-Version: 2.2
Name: seqconverter
Version: 3.4.1
Summary: Reads and writes sequence files in various formats. Performs manipulations on sequences
Home-page: https://github.com/agormp/seqconverter
Author: Anders Gorm Pedersen
Author-email: agpe@dtu.dk
Classifier: Programming Language :: Python :: 3
Classifier: License :: OSI Approved :: GNU General Public License v3 (GPLv3)
Classifier: Operating System :: OS Independent
Requires-Python: >=3.7
License-File: LICENSE
Requires-Dist: sequencelib>=2.23.1
Requires-Dist: numpy
